mozaiku/__doc.py
mozaiku/__init__.py
mozaiku/mosaic.py
mozaiku/utils.py
Mozaiku-1.0.5.dist-info/LICENSE
Mozaiku-1.0.5.dist-info/METADATA
Mozaiku-1.0.5.dist-info/WHEEL
Mozaiku-1.0.5.dist-info/top_level.txt
Mozaiku-1.0.5.dist-info/RECORD
