Metadata-Version: 2.1
Name: Mozaiku
Version: 1.0.5
Summary: Use YouTube urls, videos and folder of images to create photo mosaics with 1 line of code.
Home-page: https://github.com/Zslez/Mozaiku
Author: Cristiano Sansò
Author-email: cristiano.sanso.04@gmail.com
License: UNKNOWN
Platform: UNKNOWN
Classifier: Programming Language :: Python :: 3
Classifier: Programming Language :: Python :: 3.7
Classifier: Programming Language :: Python :: 3.8
Classifier: License :: OSI Approved :: MIT License
Classifier: Development Status :: 5 - Production/Stable
Classifier: Natural Language :: English
